etu_df_mapp/__init__.py
etu_df_mapp/main.py
etu_df_mapp/django/4.2.16/Dockerfile
etu_df_mapp/django/4.2.16/README.md
etu_df_mapp/django/4.2.16/celery_beat.sh
etu_df_mapp/django/4.2.16/celery_worker.sh
etu_df_mapp/django/4.2.16/config_dev
etu_df_mapp/django/4.2.16/config_dist
etu_df_mapp/django/4.2.16/db.sqlite3
etu_df_mapp/django/4.2.16/docker_start.sh
etu_df_mapp/django/4.2.16/gitignore
etu_df_mapp/django/4.2.16/manage.py
etu_df_mapp/django/4.2.16/start_server.sh
etu_df_mapp/django/4.2.16/uwsgi_config.ini
etu_df_mapp/django/4.2.16/app/__init__.py
etu_df_mapp/django/4.2.16/app/apps.py
etu_df_mapp/django/4.2.16/app/sub_urls.py
etu_df_mapp/django/4.2.16/app/tests.py
etu_df_mapp/django/4.2.16/app/urls.py
etu_df_mapp/django/4.2.16/app/admin/__init__.py
etu_df_mapp/django/4.2.16/app/admin/common/__init__.py
etu_df_mapp/django/4.2.16/app/admin/common/settings_admin.py
etu_df_mapp/django/4.2.16/app/admin/user/__init__.py
etu_df_mapp/django/4.2.16/app/admin/user/members_admin.py
etu_df_mapp/django/4.2.16/app/management/__init__.py
etu_df_mapp/django/4.2.16/app/management/commands/__init__.py
etu_df_mapp/django/4.2.16/app/management/commands/user_key.py
etu_df_mapp/django/4.2.16/app/migrations/0001_initial.py
etu_df_mapp/django/4.2.16/app/migrations/0002_settingconfigsmodel.py
etu_df_mapp/django/4.2.16/app/migrations/__init__.py
etu_df_mapp/django/4.2.16/app/models/__init__.py
etu_df_mapp/django/4.2.16/app/models/common/__init__.py
etu_df_mapp/django/4.2.16/app/models/common/fake_model.py
etu_df_mapp/django/4.2.16/app/models/common/settings_model.py
etu_df_mapp/django/4.2.16/app/models/user/__init__.py
etu_df_mapp/django/4.2.16/app/models/user/members.py
etu_df_mapp/django/4.2.16/app/serializers/__init__.py
etu_df_mapp/django/4.2.16/app/serializers/common/__init__.py
etu_df_mapp/django/4.2.16/app/serializers/common/fake_serializer.py
etu_df_mapp/django/4.2.16/app/serializers/user/__init__.py
etu_df_mapp/django/4.2.16/app/serializers/user/members_serializer.py
etu_df_mapp-1.0.3.dist-info/LICENSE
etu_df_mapp-1.0.3.dist-info/METADATA
etu_df_mapp-1.0.3.dist-info/WHEEL
etu_df_mapp-1.0.3.dist-info/entry_points.txt
etu_df_mapp-1.0.3.dist-info/top_level.txt
etu_df_mapp-1.0.3.dist-info/zip-safe
etu_df_mapp-1.0.3.dist-info/RECORD
