Metadata-Version: 2.1
Name: etu-df-mapp
Version: 1.0.3
Summary: 将EDFM脚手架工具，制作成为pip安装包，以方便使用
Author: Jieay
Author-email: 1016900854@qq.com
License: Apache License
Classifier: Intended Audience :: Developers
Classifier: License :: OSI Approved :: Apache Software License
Classifier: Programming Language :: Python
Classifier: Programming Language :: Python :: 3
Classifier: Programming Language :: Python :: 3.8
Classifier: Programming Language :: Python :: 3.9
Classifier: Topic :: Software Development :: Libraries
License-File: LICENSE
